llama_index/packs/dense_x_retrieval/__init__.py
llama_index/packs/dense_x_retrieval/base.py
llama_index_packs_dense_x_retrieval-0.5.1.dist-info/METADATA
llama_index_packs_dense_x_retrieval-0.5.1.dist-info/WHEEL
llama_index_packs_dense_x_retrieval-0.5.1.dist-info/licenses/LICENSE
llama_index_packs_dense_x_retrieval-0.5.1.dist-info/RECORD
