Metadata-Version: 2.4
Name: llama-index-packs-dense-x-retrieval
Version: 0.5.1
Summary: llama-index packs dense_x_retrieval integration
Author-email: Your Name <you@example.com>
Maintainer: logan-markewich
License-Expression: MIT
License-File: LICENSE
Requires-Python: <4.0,>=3.9
Requires-Dist: llama-index-core<0.15,>=0.13.0
Requires-Dist: llama-index-embeddings-openai<0.6,>=0.5.0
Requires-Dist: llama-index-llms-openai<0.6,>=0.5.0
